[
  {
    "id": "1",
    "patientId": "123456",
    "name": "K. Vijay",
    "email": "vijay@example.com",
    "phone": "9876543210",
    "gender": "MALE",
    "age": 22,
    "address": "456 Patient Street, City",
    "medicalHistory": "No significant medical history",
    "allergies": null,
    "clinicId": "1",
    "createdById": "3",
    "createdAt": "2024-01-01T00:00:00.000Z",
    "updatedAt": "2024-01-01T00:00:00.000Z"
  },
  {
    "id": "2",
    "patientId": "454575",
    "name": "P. Sandeep",
    "email": "sandeep@example.com",
    "phone": "9876543215",
    "gender": "MALE",
    "age": 30,
    "address": "789 Patient Avenue, City",
    "medicalHistory": null,
    "allergies": null,
    "clinicId": "1",
    "createdById": "3",
    "createdAt": "2024-01-01T00:00:00.000Z",
    "updatedAt": "2024-01-01T00:00:00.000Z"
  },
  {
    "id": "3",
    "patientId": "787764",
    "name": "Ch. Asritha",
    "email": "asritha@example.com",
    "phone": "9876543216",
    "gender": "FEMALE",
    "age": 25,
    "address": "321 Patient Road, City",
    "medicalHistory": null,
    "allergies": null,
    "clinicId": "1",
    "createdById": "3",
    "createdAt": "2024-01-01T00:00:00.000Z",
    "updatedAt": "2024-01-01T00:00:00.000Z"
  },
  {
    "id": "4",
    "patientId": "454215",
    "name": "P. Ravi",
    "email": "ravi@example.com",
    "phone": "9876543217",
    "gender": "MALE",
    "age": 32,
    "address": "123 Patient Lane, City",
    "medicalHistory": "Kidney disease",
    "allergies": "Penicillin",
    "clinicId": "1",
    "createdById": "3",
    "createdAt": "2024-01-02T00:00:00.000Z",
    "updatedAt": "2024-01-02T00:00:00.000Z"
  },
  {
    "id": "5",
    "patientId": "498465",
    "name": "A. Srikanth",
    "email": "srikanth@example.com",
    "phone": "9876543218",
    "gender": "MALE",
    "age": 32,
    "address": "456 Patient Circle, City",
    "medicalHistory": "Heart problem",
    "allergies": null,
    "clinicId": "1",
    "createdById": "3",
    "createdAt": "2024-01-02T00:00:00.000Z",
    "updatedAt": "2024-01-02T00:00:00.000Z"
  }
]